vlcyt/__init__.py
vlcyt/__main__.py
vlcyt/app.py
vlcyt/command_handler.py
vlcyt/file_helpers.py
vlcyt/lyrics_scraper.py
VLCYT-1.9.dist-info/LICENSE.md
VLCYT-1.9.dist-info/METADATA
VLCYT-1.9.dist-info/WHEEL
VLCYT-1.9.dist-info/top_level.txt
VLCYT-1.9.dist-info/RECORD
