Metadata-Version: 2.1
Name: VLCYT
Version: 1.9
Summary: Stream your YouTube playlist in VLC behind the scenes from the command line.
Home-page: https://github.com/hillt03/VLCYT
Author: Timothy Hill Jr
License: MIT
Keywords: youtube vlc stream playlist
Platform: UNKNOWN
Classifier: Programming Language :: Python :: 3
Classifier: License :: OSI Approved :: MIT License
Classifier: Operating System :: Microsoft :: Windows
Requires-Python: >=3.8
Requires-Dist: colorama (>=0.4.4)
Requires-Dist: pafy (>=0.5.5)
Requires-Dist: python-vlc (>=3.0.12118)
Requires-Dist: youtube-dl (>=2021.4.26)
Requires-Dist: pyperclip (>=1.8.2)
